README.txt
setup.py
tests/__init__.py
tests/testsuite.py
todopy/__init__.py
todopy/filter.py
todopy/formatter.py
todopy/model.py
todopy/munger.py
todopy/options.py
todopy/reader.py
todopy/todopy.py
todopy/writer.py
todopy.egg-info/PKG-INFO
todopy.egg-info/SOURCES.txt
todopy.egg-info/dependency_links.txt
todopy.egg-info/entry_points.txt
todopy.egg-info/requires.txt
todopy.egg-info/top_level.txt