Metadata-Version: 1.0
Name: todopy
Version: 1.0.2
Summary: Todo.txt in Python
Home-page: https://bitbucket.org/Ilkka/todopy
Author: Ilkka Laukkanen
Author-email: ilkka.s.laukkanen@gmail.com
License: GPLv3
Keywords: todo gtd todo.txt
Platform: UNKNOWN
Classifier: Development Status :: 5 - Production/Stable
Classifier: Topic :: Utilities
Classifier: Environment :: Console
Classifier: Intended Audience :: End Users/Desktop
Classifier: License :: OSI Approved :: GNU General Public License (GPL)
